adiskreader_secretsdump/__init__.py
adiskreader_secretsdump/_version.py
adiskreader_secretsdump/utils.py
adiskreader_secretsdump/examples/__init__.py
adiskreader_secretsdump/examples/console.py
adiskreader_secretsdump/modules/__init__.py
adiskreader_secretsdump/modules/ntds/__init__.py
adiskreader_secretsdump/modules/registry/__init__.py
adiskreader_secretsdump-0.0.1.dist-info/METADATA
adiskreader_secretsdump-0.0.1.dist-info/WHEEL
adiskreader_secretsdump-0.0.1.dist-info/entry_points.txt
adiskreader_secretsdump-0.0.1.dist-info/top_level.txt
adiskreader_secretsdump-0.0.1.dist-info/zip-safe
adiskreader_secretsdump-0.0.1.dist-info/RECORD
